httpx_gssapi/__init__.py
httpx_gssapi/_version.py
httpx_gssapi/exceptions.py
httpx_gssapi/gssapi_.py
httpx_gssapi/py.typed
httpx_gssapi-0.6.dist-info/licenses/AUTHORS
httpx_gssapi-0.6.dist-info/licenses/LICENSE
httpx_gssapi-0.6.dist-info/METADATA
httpx_gssapi-0.6.dist-info/WHEEL
httpx_gssapi-0.6.dist-info/top_level.txt
httpx_gssapi-0.6.dist-info/RECORD
