Metadata-Version: 2.4
Name: httpx-gssapi
Version: 0.6
Summary: A Python GSSAPI authentication handler for HTTPX
Home-page: https://github.com/pythongssapi/httpx-gssapi
Author: Ian Cordasco, Cory Benfield, Michael Komitee, Robbie Harwood, Roger Aiudi
Author-email: aiudirog@gmail.com
License: MIT
Keywords: httpx,gssapi,kerberos
Classifier: Development Status :: 5 - Production/Stable
Classifier: Intended Audience :: Developers
Classifier: License :: OSI Approved :: ISC License (ISCL)
Classifier: Programming Language :: Python :: 3.9
Classifier: Programming Language :: Python :: 3.10
Classifier: Programming Language :: Python :: 3.11
Classifier: Programming Language :: Python :: 3.12
Classifier: Programming Language :: Python :: 3.13
Classifier: Topic :: Software Development :: Libraries :: Python Modules
Requires-Python: >=3.9
License-File: LICENSE
License-File: AUTHORS
Requires-Dist: httpx<0.29,>=0.16
Requires-Dist: gssapi
Provides-Extra: test
Requires-Dist: pytest; extra == "test"
Requires-Dist: k5test; extra == "test"
Provides-Extra: all
Requires-Dist: pytest; extra == "all"
Requires-Dist: k5test; extra == "all"
Dynamic: description
Dynamic: description-content-type
Dynamic: license-file
